discrete_kit/__init__.py
discrete_kit/app_create_shape_json.py
discrete_kit/configuration/__init__.py
discrete_kit/configuration/config.py
discrete_kit/functions/__init__.py
discrete_kit/functions/metadata_convertor.py
discrete_kit/functions/shape_functions.py
discrete_kit/jsons/__init__.py
discrete_kit/tests/__init__.py
discrete_kit/tests/sandbox.py
discrete_kit/validator/__init__.py
discrete_kit/validator/json_compare_pycsw.py
discrete_kit/validator/schema_validator.py
discrete_kit/validator/schema/__init__.py
mc_discrete_kit-0.0.30.dist-info/LICENSE
mc_discrete_kit-0.0.30.dist-info/METADATA
mc_discrete_kit-0.0.30.dist-info/WHEEL
mc_discrete_kit-0.0.30.dist-info/top_level.txt
mc_discrete_kit-0.0.30.dist-info/RECORD
