Metadata-Version: 2.1
Name: mc-discrete-kit
Version: 0.0.30
Summary: Map colonies discrete-kit for geo data usage
Home-page: https://github.com/MapColonies/automation-discrete-kit.git
Author: MC
License: UNKNOWN
Platform: UNKNOWN
Classifier: Programming Language :: Python :: 3
Classifier: License :: OSI Approved :: MIT License
Classifier: Operating System :: OS Independent
Requires-Python: >=3.6
License-File: LICENSE
Requires-Dist: setuptools (~=50.3.2)
Requires-Dist: wheel
Requires-Dist: geopandas
Requires-Dist: Fiona
Requires-Dist: jsonschema
Requires-Dist: mc-automation-tools
